LICENSE.txt
MANIFEST.in
README.md
setup.cfg
setup.py
banqup_uc/__init__.py
banqup_uc/api.py
banqup_uc/authhandler.py
banqup_uc/cachehandler.py
banqup_uc/config.py
banqup_uc/helpers.py
banqup_uc/cache/__init__.py
banqup_uc/constants/constants.py
banqup_uc/constants/errors.py
banqup_uc/endpoints/__init__.py
banqup_uc/endpoints/base.py
banqup_uc/endpoints/purchaseinvoices.py
banqup_uc/models/__init__.py
banqup_uc/models/base.py
banqup_uc/models/errors.py
banqup_uc/models/intakeresponses.py
python_banqup_uc_api.egg-info/PKG-INFO
python_banqup_uc_api.egg-info/SOURCES.txt
python_banqup_uc_api.egg-info/dependency_links.txt
python_banqup_uc_api.egg-info/requires.txt
python_banqup_uc_api.egg-info/top_level.txt